zhangsan12345abc/MyDD.py
zhangsan12345abc/__init__.py
zhangsan12345abc-0.1.6.dist-info/LICENSE
zhangsan12345abc-0.1.6.dist-info/METADATA
zhangsan12345abc-0.1.6.dist-info/WHEEL
zhangsan12345abc-0.1.6.dist-info/top_level.txt
zhangsan12345abc-0.1.6.dist-info/RECORD
