Metadata-Version: 2.1
Name: zhangsan12345abc
Version: 0.1.6
Summary: 上传自定义包
Author: zhangsan12345
Author-email: zhangsan12345@qq.com
License: MIT
Platform: UNKNOWN
Classifier: License :: OSI Approved :: MIT License
Classifier: Programming Language :: Python
Classifier: Programming Language :: Python :: 3
License-File: LICENSE
